{"COMBINATIONS":{
		"E_001":{
			"invalid" : ["C_001","D_001"],
			"valid" : []
		},
		"G_001":{
			"invalid" : ["MA_001","M_002","M_003","M_004","M_005","M_006","M_007","M_008","M_009","M_010","M_011","M_012","NA_001","N_002","N_003","N_004","N_005","N_006","N_007","N_008","N_009","N_010","N_011","N_012","P_001","Y_001"],
			"valid" : []
		},
		"MA_001":{
			"invalid" : ["G_001","M_002","M_003","M_004","M_005","M_006","M_007","M_008","M_009","M_010","M_011","M_012"],
			"valid" : []
		},
		"M_002":{
			"invalid" : ["G_001","MA_001"],
			"valid" : []
		},
		"M_003":{
			"invalid" : ["G_001","MA_001"],
			"valid" : []
		},
		"M_004":{
			"invalid" : ["G_001","MA_001"],
			"valid" : []
		},
		"M_005":{
			"invalid" : ["G_001","MA_001"],
			"valid" : []
		},
		"M_006":{
			"invalid" : ["G_001","MA_001"],
			"valid" : []
		},
		"M_007":{
			"invalid" : ["G_001","MA_001"],
			"valid" : []
		},
		"M_008":{
			"invalid" : ["G_001","MA_001"],
			"valid" : []
		},
		"M_009":{
			"invalid" : ["G_001","MA_001"],
			"valid" : []
		},
		"M_010":{
			"invalid" : ["G_001","MA_001"],
			"valid" : []
		},
		"M_011":{
			"invalid" : ["G_001","MA_001"],
			"valid" : []
		},
		"M_012":{
			"invalid" : ["G_001","MA_001"],
			"valid" : []
		},
		"NA_001":{
			"invalid" : ["G_001","N_002","N_003","N_004","N_005","N_006","N_007","N_008","N_009","N_010","N_011","N_012"],
			"valid" : []
		},
		"N_002":{
			"invalid" : ["G_001","NA_001"],
			"valid" : []
		},
		"N_003":{
			"invalid" : ["G_001","NA_001"],
			"valid" : []
		},
		"N_004":{
			"invalid" : ["G_001","NA_001"],
			"valid" : []
		},
		"N_005":{
			"invalid" : ["G_001","NA_001"],
			"valid" : []
		},
		"N_006":{
			"invalid" : ["G_001","NA_001"],
			"valid" : []
		},
		"N_007":{
			"invalid" : ["G_001","NA_001"],
			"valid" : []
		},
		"N_008":{
			"invalid" : ["G_001","NA_001"],
			"valid" : []
		},
		"N_009":{
			"invalid" : ["G_001","NA_001"],
			"valid" : []
		},
		"N_010":{
			"invalid" : ["G_001","NA_001"],
			"valid" : []
		},
		"N_011":{
			"invalid" : ["G_001","NA_001"],
			"valid" : []
		},
		"N_012":{
			"invalid" : ["G_001","NA_001"],
			"valid" : []
		},
		"P_001":{
			"invalid" : ["G_001","Y_001"],
			"valid" : []
		},
		"Y_001":{
			"invalid" : ["G_001","P_001"],
			"valid" : []
		},
		"Q_001":{
			"invalid" : ["Z_001"],
			"valid" : []
		},
		"Z_001":{
			"invalid" : ["Q_001"],
			"valid" : []
		}
	}
}